matildapeak_pyconf-2018.2.dist-info/METADATA
matildapeak_pyconf-2018.2.dist-info/RECORD
matildapeak_pyconf-2018.2.dist-info/WHEEL
matildapeak_pyconf-2018.2.dist-info/entry_points.txt
matildapeak_pyconf-2018.2.dist-info/top_level.txt
pyconf/__init__.py
pyconf/__main__.py
pyconf/pyconf.py
