Metadata-Version: 2.1
Name: matildapeak-pyconf
Version: 2018.2
Summary: An Autoconf-like configuration tool
Home-page: https://gitlab.com/matilda.peak/pyconf
Author: Alan Christie
Author-email: alan.christie@matildapeak.com
License: Copyright (C) 2018 Alan Christie. All rights reserved.
Keywords: configuration
Platform: any
Classifier: Development Status :: 5 - Production/Stable
Classifier: Environment :: Console
Classifier: Intended Audience :: Developers
Classifier: License :: Other/Proprietary License
Classifier: Programming Language :: Python :: 3.6
Classifier: Topic :: System :: Installation/Setup
Classifier: Operating System :: POSIX :: Linux
Requires-Dist: PyYAML (==3.13)
